mykhcolors/__about__.py
mykhcolors/__init__.py
mykhcolors/colors.py
mykhcolors-0.5.4.dist-info/METADATA
mykhcolors-0.5.4.dist-info/WHEEL
mykhcolors-0.5.4.dist-info/entry_points.txt
mykhcolors-0.5.4.dist-info/licenses/LICENSE.txt
mykhcolors-0.5.4.dist-info/RECORD
