Metadata-Version: 2.4
Name: mykhcolors
Version: 0.5.4
Summary: Studying github CI/CD
Project-URL: Documentation, https://github.com/khtestingo/testing_cicd#readme
Project-URL: Issues, https://github.com/khtestingo/testing_cicd
Project-URL: Source, https://github.com/khtestingo/testing_cicd/mykhcolors
Author-email: khaz <pykhaz@o2.pl>
License-Expression: MIT
License-File: LICENSE.txt
Keywords: CD,CI,ansi codes,github,terminal
Requires-Python: >=3.8
